vera_testframework/__init__.py
vera_testframework/_version.py
vera_testframework/utils.py
vera_testframework/pyspark/__init__.py
vera_testframework/pyspark/referentiedata.py
vera_testframework-1.0.0.dist-info/licenses/LICENSE
vera_testframework-1.0.0.dist-info/METADATA
vera_testframework-1.0.0.dist-info/WHEEL
vera_testframework-1.0.0.dist-info/top_level.txt
vera_testframework-1.0.0.dist-info/RECORD
