Metadata-Version: 2.4
Name: vera-testframework
Version: 1.0.0
Summary: Testframework voor VERA referentiedata
Author-email: Woonstad Rotterdam <info@woonstadrotterdam.nl>, Tomer Gabay <tomer.gabay@woonstadrotterdam.nl>
License: MIT License
Project-URL: Homepage, https://github.com/woonstadrotterdam/vera-testframework
Project-URL: Issues, https://github.com/woonstadrotterdam/vera-testframework/issues
Keywords: vera,referentiedata,test,testframework,aedes
Classifier: Programming Language :: Python :: 3.9
Classifier: Programming Language :: Python :: 3.10
Classifier: Programming Language :: Python :: 3.11
Classifier: Programming Language :: Python :: 3.12
Classifier: License :: OSI Approved :: MIT License
Classifier: Operating System :: OS Independent
Requires-Python: >=3.9.5
License-File: LICENSE
Requires-Dist: pyspark-testframework>=3.0.0
Requires-Dist: requests>=2.0.0
Provides-Extra: test
Requires-Dist: pre-commit==3.*; extra == "test"
Requires-Dist: pytest==8.*; extra == "test"
Requires-Dist: pytest-cov==5.*; extra == "test"
Requires-Dist: pyspark==3.*; extra == "test"
Provides-Extra: dev
Requires-Dist: vera-testframework[test]; extra == "dev"
Requires-Dist: ruff==0.14.1; extra == "dev"
Dynamic: license-file
